fasthr/__init__.py
fasthr/main.py
fasthr-1.0.0.dist-info/METADATA
fasthr-1.0.0.dist-info/WHEEL
fasthr-1.0.0.dist-info/top_level.txt
fasthr-1.0.0.dist-info/RECORD
