Metadata-Version: 2.1
Name: fasthr
Version: 1.0.0
Home-page: https://github.com/fanzou99/FastHR
Author: Fan Zou
Author-email: fuz64@psu.edu
Classifier: Programming Language :: Python :: 3
Classifier: License :: OSI Approved :: MIT License
Requires-Dist: numpy
Requires-Dist: scipy
